{
  "tasks": [
    {
      "taskName": "Sleep",
      "taskPriority": "High",
      "taskStatus": "completed",
      "id": 1
    },
    {
      "taskName": "Eat",
      "taskPriority": "High",
      "taskStatus": "completed",
      "id": 3
    },
    {
      "taskName": "Complete HomeWork",
      "taskPriority": "High",
      "taskStatus": "incomplete",
      "id": 4
    },
    {
      "taskName": "Complete Assignment",
      "taskPriority": "High",
      "taskStatus": "incomplete",
      "id": 5
    },
    {
      "taskName": "Meet Aunt Alexa",
      "taskPriority": "Medium",
      "taskStatus": "completed",
      "id": 6
    },
    {
      "taskName": "Kill Alaxendar ",
      "taskPriority": "Low",
      "taskStatus": "incomplete",
      "id": 7
    },
    {
      "taskName": "Buy Football",
      "taskPriority": "Medium",
      "taskStatus": "incomplete",
      "id": 8
    },
    {
      "taskName": "Play table Tennis",
      "taskPriority": "Low",
      "taskStatus": "completed",
      "id": 9
    },
    {
      "taskName": "sfnkjdfhdljkfha",
      "taskPriority": "High",
      "taskStatus": "incomplete",
      "id": 10
    },
    {
      "taskName": "sfnkjdfhdfdfjkdhfjdkahd;gjkdhfljkfha",
      "taskPriority": "High",
      "taskStatus": "completed",
      "id": 11
    }
  ]
}